filename_to_fontawesome/__init__.py
filename_to_fontawesome/filename_to_fontawesome.py
filename_to_fontawesome/fileextensions/__init__.py
filename_to_fontawesome/fileextensions/extensions.py
filename_to_fontawesome/fileextensions/mimes.py
filename_to_fontawesome/fontawesome/__init__.py
filename_to_fontawesome/fontawesome/fontawesome.py
filename_to_fontawesome-0.4.0.dist-info/DESCRIPTION.rst
filename_to_fontawesome-0.4.0.dist-info/METADATA
filename_to_fontawesome-0.4.0.dist-info/RECORD
filename_to_fontawesome-0.4.0.dist-info/WHEEL
filename_to_fontawesome-0.4.0.dist-info/metadata.json
filename_to_fontawesome-0.4.0.dist-info/top_level.txt
