Metadata-Version: 2.0
Name: filename-to-fontawesome
Version: 0.4.0
Summary: Helper to transmorm a filename to the fontawesome tag
Home-page: https://github.com/kiki407/filename_to_fontawesome
Author: Kilian Rault
Author-email: kiki407@hotmail.com
License: MIT license
Keywords: filename mime fontawesome
Platform: UNKNOWN
Classifier: Development Status :: 2 - Pre-Alpha
Classifier: Intended Audience :: Developers
Classifier: License :: OSI Approved :: MIT License
Classifier: Natural Language :: English
Classifier: Programming Language :: Python :: 2
Classifier: Programming Language :: Python :: 2.7
Classifier: Programming Language :: Python :: 3
Classifier: Programming Language :: Python :: 3.4
Classifier: Programming Language :: Python :: 3.5
Classifier: Programming Language :: Python :: 3.6
Requires-Python: >=2.7
